ml_gcam/__init__.py
ml_gcam/__main__.py
ml_gcam/cli/__init__.py
ml_gcam/cli/core.py
ml_gcam/cli/data.py
ml_gcam/cli/debug.py
ml_gcam/cli/evaluate.py
ml_gcam/cli/interpolate.py
ml_gcam/cli/options.py
ml_gcam/cli/plot.py
ml_gcam/cli/sensitivity.py
ml_gcam/cli/table.py
ml_gcam/cli/training.py
ml_gcam/config/__init__.py
ml_gcam/core/__init__.py
ml_gcam/core/extract.py
ml_gcam/core/input.py
ml_gcam/core/interpolate.py
ml_gcam/core/output.py
ml_gcam/data/__init__.py
ml_gcam/data/dataset.py
ml_gcam/data/enums.py
ml_gcam/data/experiment.py
ml_gcam/data/normalization.py
ml_gcam/data/scenarios.py
ml_gcam/data/targets.py
ml_gcam/data/wandb.py
ml_gcam/debug/__init__.py
ml_gcam/emulator/__init__.py
ml_gcam/emulator/model.py
ml_gcam/evaluate/__init__.py
ml_gcam/evaluate/cartesian.py
ml_gcam/evaluate/fraction_binary.py
ml_gcam/evaluate/metrics.py
ml_gcam/evaluate/sample_size.py
ml_gcam/evaluate/sensitivity.py
ml_gcam/inference/__init__.py
ml_gcam/inference/inference.py
ml_gcam/logging/__init__.py
ml_gcam/notebooks/__init__.py
ml_gcam/notebooks/explore.py
ml_gcam/plot/__init__.py
ml_gcam/plot/fraction_binary.py
ml_gcam/plot/geo.py
ml_gcam/plot/previous.py
ml_gcam/plot/r2.py
ml_gcam/plot/sample_size.py
ml_gcam/plot/sensitivity.py
ml_gcam/plot/targets.py
ml_gcam/renewable_adoption/__init__.py
ml_gcam/renewable_adoption/evaluate.py
ml_gcam/sensitivity/__init__.py
ml_gcam/table/__init__.py
ml_gcam/table/sensitivity.py
ml_gcam/table/table.py
ml_gcam/training/__init__.py
ml_gcam/training/logger.py
ml_gcam/training/runner.py
ml_gcam/training/sweep.py
ml_gcam/training/train.py
tests/__init__.py
tests/test_cli.py
tests/test_config.py
tests/test_data_enums.py
tests/test_dataset.py
tests/test_evaluation.py
tests/test_inference.py
tests/test_mixed.py
tests/test_targets.py
tests/test_training.py
tests/test_wandb.py
ml_gcam-0.2.2.dist-info/METADATA
ml_gcam-0.2.2.dist-info/WHEEL
ml_gcam-0.2.2.dist-info/entry_points.txt
ml_gcam-0.2.2.dist-info/top_level.txt
ml_gcam-0.2.2.dist-info/RECORD
