Metadata-Version: 2.1
Name: ml-gcam
Version: 0.2.2
Summary: gcam emulator
Home-page: https://github.com/hutchresearch/ml_climate_gcam22/tree/documentation
Author: HutchResearch
Author-email: brian.hutchinson@wwu.edu
License: MIT
Classifier: License :: OSI Approved :: MIT License
Classifier: Programming Language :: Python :: 3.10
Classifier: Operating System :: OS Independent
Requires-Python: >=3.10
Requires-Dist: torch
Requires-Dist: pytorch-cuda ==1.12.1
Requires-Dist: einops
Requires-Dist: accelerate
Requires-Dist: torchtyping
Requires-Dist: scikit-learn
Requires-Dist: seaborn
Requires-Dist: tensorboard
Requires-Dist: wandb
Requires-Dist: polars >=0.20.19
Requires-Dist: pandas
Requires-Dist: pyarrow
Requires-Dist: marimo
Requires-Dist: gcamreader >=1.4.0
Requires-Dist: pytest
Requires-Dist: pytest-cov
Requires-Dist: click
Requires-Dist: rich
Requires-Dist: tqdm
Requires-Dist: python-dotenv
Requires-Dist: python-configuration[toml]
Requires-Dist: lxml
Requires-Dist: geopandas >=0.9.0
